zabbix_elasticsearch/__init__.py
zabbix_elasticsearch/zabbix_elasticsearch.py
zabbix_elasticsearch-0.1.0.data/data/docs/default.conf
zabbix_elasticsearch-0.1.0.dist-info/LICENCE
zabbix_elasticsearch-0.1.0.dist-info/METADATA
zabbix_elasticsearch-0.1.0.dist-info/WHEEL
zabbix_elasticsearch-0.1.0.dist-info/entry_points.txt
zabbix_elasticsearch-0.1.0.dist-info/top_level.txt
zabbix_elasticsearch-0.1.0.dist-info/RECORD
